setup.py
syncle/__init__.py
syncle/syncle.py
syncle.egg-info/PKG-INFO
syncle.egg-info/SOURCES.txt
syncle.egg-info/dependency_links.txt
syncle.egg-info/entry_points.txt
syncle.egg-info/requires.txt
syncle.egg-info/top_level.txt