Metadata-Version: 1.0
Name: syncle
Version: 0.1
Summary: Single file synchronization tool
Home-page: https://github.com/rdolgushin/syncle
Author: Roman Dolgushin
Author-email: rd@roman-dolgushin.ru
License: MIT
Platform: UNKNOWN
Classifier: Topic :: Utilities
Classifier: Topic :: Communications :: File Sharing
Classifier: Environment :: Console
Classifier: License :: OSI Approved :: MIT License
Classifier: Operating System :: POSIX
